hero24/data_structures/CircularList.py
hero24/data_structures/DictGraph.py
hero24/data_structures/MatrixGraph.py
hero24/data_structures/Queue.py
hero24/data_structures/__init__.py
hero24/data_structures/setup.py
hero24.data_structures-1.12.dist-info/METADATA
hero24.data_structures-1.12.dist-info/WHEEL
hero24.data_structures-1.12.dist-info/top_level.txt
hero24.data_structures-1.12.dist-info/RECORD
