Metadata-Version: 2.1
Name: hero24.data_structures
Version: 1.12
Summary: A set of various data structures
Author: hero24
Author-email: hero24 <hero24@interia.pl>
Project-URL: Homepage, https://github.com/hero24/Data-Structures/
Project-URL: Issues, https://github.com/hero24/Data-Sturctures/issues/
Classifier: Programming Language :: Python :: 3
Classifier: License :: OSI Approved :: MIT License
Classifier: Operating System :: OS Independent
Requires-Python: >=3.5
